polymod.pypy38-pp73-x86_64-linux-gnu.so
SpectralToolbox/HeterogeneousSparseGrids.py
SpectralToolbox/__init__.py
SpectralToolbox/SparseGrids.py
SpectralToolbox/SpectralND.py
SpectralToolbox/_version.py
SpectralToolbox/Misc.py
SpectralToolbox/Stroud.py
SpectralToolbox/Spectral1D/auxiliary.py
SpectralToolbox/Spectral1D/__init__.py
SpectralToolbox/Spectral1D/OrthogonalFunctions.py
SpectralToolbox/Spectral1D/AlgebraicPolynomials.py
SpectralToolbox/Spectral1D/OrthogonalPolynomials.py
SpectralToolbox/Spectral1D/Constants.py
SpectralToolbox/Spectral1D/LagrangePolynomials.py
SpectralToolbox/Spectral1D/NonOrthogonalBasis.py
SpectralToolbox/Spectral1D/AbstractClasses.py
SpectralToolbox/Spectral1D/LinearInterpolation.py
SpectralToolbox/Spectral1D/XML/schema/basis.xsd
SpectralToolbox/tests/plot_integrated_squared.py
SpectralToolbox/tests/test_all.py
SpectralToolbox/tests/__init__.py
SpectralToolbox/tests/test_squared_orth.py
SpectralToolbox/tests/test_spectral1d.py
spectraltoolbox-2.0.3.dist-info/RECORD
spectraltoolbox-2.0.3.dist-info/top_level.txt
spectraltoolbox-2.0.3.dist-info/METADATA
spectraltoolbox-2.0.3.dist-info/zip-safe
spectraltoolbox-2.0.3.dist-info/WHEEL
