Metadata-Version: 2.1
Name: spectraltoolbox
Version: 2.0.3
Summary: Toolbox for building spectral methods
Author-email: Daniele Bigoni <dabi@limitcycle.it>
License: LGPL
Requires-Python: >=3.8
Requires-Dist: numpy
Requires-Dist: scipy
Requires-Dist: orthpol-light
